DataScienceHelper.py
datasciencehelper-1.0.0.dist-info/LICENSE
datasciencehelper-1.0.0.dist-info/METADATA
datasciencehelper-1.0.0.dist-info/WHEEL
datasciencehelper-1.0.0.dist-info/top_level.txt
datasciencehelper-1.0.0.dist-info/RECORD
