Metadata-Version: 2.1
Name: datasciencehelper
Version: 1.0.0
Summary: A helper library that saves time.
Home-page: UNKNOWN
Author: UNKNOWN
Author-email: UNKNOWN
License: UNKNOWN
Platform: UNKNOWN
